pyProxyrack/__init__.py
pyProxyrack/exceptions.py
pyProxyrack/proxyrack.py
pyProxyrack-0.1.1.dist-info/LICENSE
pyProxyrack-0.1.1.dist-info/METADATA
pyProxyrack-0.1.1.dist-info/WHEEL
pyProxyrack-0.1.1.dist-info/top_level.txt
pyProxyrack-0.1.1.dist-info/RECORD
