Metadata-Version: 2.1
Name: pyProxyrack
Version: 0.1.1
Summary: UNOFFICIAL Python bindings for Proxyrack Dashboard API
Home-page: https://github.com/coder-amogh/pyProxyrack
Author: coder-amogh (Amogh Datar)
License: UNKNOWN
Project-URL: Bug Tracker, https://github.com/coder-amogh/pyProxyrack/issues
Keywords: python,proxyrack,passive income,Proxyrack api,Proxyrack dashboard,python proxyrack,proxyrack mon
Platform: UNKNOWN
Classifier: Development Status :: 5 - Production/Stable
Classifier: Intended Audience :: Developers
Classifier: Programming Language :: Python :: 3
Classifier: Operating System :: OS Independent
Requires-Dist: requests
Requires-Dist: pySocks
